LICENSE.txt
setup.py
code/__init__.py
code/setup.py
khalid_homed1.egg-info/PKG-INFO
khalid_homed1.egg-info/SOURCES.txt
khalid_homed1.egg-info/dependency_links.txt
khalid_homed1.egg-info/top_level.txt