Metadata-Version: 2.1
Name: khalid-homed1
Version: 0.0.1
Summary: simpel library in python
Author: khalidhomed
Author-email: 
Classifier: Programming Language :: Python :: 3
Classifier: License :: OSI Approved :: MIT License
Classifier: Operating System :: OS Independent
License-File: LICENSE.txt
